Docs/#module_cant_find_sister.py.txt
Docs/ACES_Graphics_talk.docx
Docs/ACES_VOLUNTEER_GRAPHICS_FOR_THE_BLIND_short.docx
Docs/GFTB_blind_example.docx
Docs/GFTB_blind_example.png
Docs/GFTB_visual_example.docx
Docs/GFTB_visual_example.png
Docs/Magnification_Demo.PNG
Docs/Programming Beginnings Sighted to Blind.docx
Docs/Sixty_Second-Intro.docx
Docs/X.docx
Docs/braille_turtle_spokes_bw.PNG
Docs/braille_turtle_spokes_pgm.PNG
Docs/braille_turtle_spokes_td.PNG
Docs/braille_turtle_spokes_to.PNG
Docs/build_local_wheel.txt
Docs/contact_info.docx
Docs/graphics_braille_dependencies.txt
Docs/graphics_braille_import_to_run_exit.txt
Docs/graphics_braille_install_not_latest.txt
Docs/graphics_braille_install_test.txt
Docs/graphics_braille_run.txt
Docs/graphics_braille_test.txt
Docs/graphics_braille_test_run.txt
Docs/graphics_braille_test_screenshot.png
Docs/import graphics_braille.txt
Docs/install_from_whl.txt
Docs/missing_path_descriptions.txt
Docs/missing_path_screen_shot.png
Docs/pypi_build_graphics_braille.txt
Docs/pypi_graphics_braille_install_run.png
Docs/pypi_install_import_graphics_braille.txt
Docs/pypi_issues.txt
Docs/pypi_upload_test_graphics_braille_verbose.txt
Docs/pyprojec_toml_files_testing.txt
Docs/run_test.txt.txt
Docs/spokes_audio_braille_window.png
Docs/spokes_audio_window.PNG
Docs/spokes_print_output.PNG
Docs/spokes_program_code_.png
Docs/spokes_terminal_output.txt
Docs/spokes_text_map.png
Docs/spokes_turtle_display.png
Docs/square_loop.png
Docs/wxpython_install_error.txt.txt
Docs/wxpython_install_error_fix.txt
Docs/x_show_square_without_and_with_hack.txt
Docs/~$ES_VOLUNTEER_GRAPHICS_FOR_THE_BLIND_short.docx
Docs/~$TB_blind_example.docx
Docs/~$TB_visual_example.docx
Docs/~$X.docx
Docs/~WRL2471.tmp
gb_exercises/show_square_loop_colors.py
gb_exercises/show_square_loop_colors_w80.py
gb_exercises/braille/show_spokes_braille.py
gb_exercises/braille/show_square_loop_colors_braille.py
gb_exercises/braille/show_square_loop_colors_braille_star.py
gb_exercises/graphics_braille.egg-info/PKG-INFO
gb_exercises/graphics_braille.egg-info/SOURCES.txt
gb_exercises/graphics_braille.egg-info/dependency_links.txt
gb_exercises/graphics_braille.egg-info/entry_points.txt
gb_exercises/graphics_braille.egg-info/requires.txt
gb_exercises/graphics_braille.egg-info/top_level.txt
graphics_braille-0.2.2.dist-info/licenses/LICENSE.md
graphics_braille-0.2.2.dist-info/METADATA
graphics_braille-0.2.2.dist-info/WHEEL
graphics_braille-0.2.2.dist-info/entry_points.txt
graphics_braille-0.2.2.dist-info/top_level.txt
graphics_braille-0.2.2.dist-info/RECORD
