Metadata-Version: 2.4
Name: graphics_braille
Version: 0.1.44.dev13
Summary: Create Braille maps for simple Turtle program output
Author-email: Ray Smith <raysmith619@gmail.com>
License-Expression: MIT
Project-URL: Homepage, https://github.com/raysmith619/graphics_braille
Project-URL: Issues, https://github.com/raysmith619/graphics_braille/issues
Classifier: Programming Language :: Python :: 3
Classifier: Operating System :: OS Independent
Requires-Python: <4.1,>=3.9
License-File: LICENSE.md
Requires-Dist: numpy
Requires-Dist: pysinewave
Requires-Dist: pyttsx3
Requires-Dist: pyttsx4
Requires-Dist: sounddevice
Requires-Dist: wxpython
Requires-Dist: DistInfo-ReadMe
Dynamic: license-file
